ascii_cat/__init__.py
ascii_cat/ascii-cats.jsonl
ascii_cat/cli.py
ascii_cat/scraper.py
catmemes-0.2.1.dist-info/LICENSE
catmemes-0.2.1.dist-info/METADATA
catmemes-0.2.1.dist-info/WHEEL
catmemes-0.2.1.dist-info/entry_points.txt
catmemes-0.2.1.dist-info/RECORD
