Metadata-Version: 2.3
Name: catmemes
Version: 0.2.1
Summary: Retrieve famous cat memes (ascii and image)
Author: pielet
Author-email: syjia0325@gmail.com
Requires-Python: >=3.10
Classifier: Programming Language :: Python :: 3
Classifier: Programming Language :: Python :: 3.10
Classifier: Programming Language :: Python :: 3.11
Classifier: Programming Language :: Python :: 3.12
Classifier: Programming Language :: Python :: 3.13
Requires-Dist: beautifulsoup4 (>=4.13.4,<5.0.0)
Requires-Dist: datasets (>=2.0.0)
Requires-Dist: numpy (>=2.3.2)
Requires-Dist: requests (>=2.32.4,<3.0.0)
Requires-Dist: setuptools (>=78.1.1)
Requires-Dist: urllib3 (>=2.5.0)
